wafec_tests_openstack_base-0.1.1-py3.8-nspkg.pth
wafec_tests_openstack_base/interception.py
wafec_tests_openstack_base/interception_tests.py
wafec_tests_openstack_base/utils.py
wafec_tests_openstack_base/utils_tests.py
wafec_tests_openstack_base/clients/__init__.py
wafec_tests_openstack_base/clients/client_base.py
wafec_tests_openstack_base/clients/interception_agent_client.py
wafec_tests_openstack_base/clients/interception_agent_client_tests.py
wafec_tests_openstack_base/clients/interception_controller_client.py
wafec_tests_openstack_base/exceptions/__init__.py
wafec_tests_openstack_base/exceptions/argument_exception.py
wafec_tests_openstack_base/exceptions/client_exception.py
wafec_tests_openstack_base/exceptions/exception_base.py
wafec_tests_openstack_base/exceptions/fault_not_found_exception.py
wafec_tests_openstack_base/exceptions/method_not_found_exception.py
wafec_tests_openstack_base/fault/__init__.py
wafec_tests_openstack_base/fault/base_operator.py
wafec_tests_openstack_base/fault/text_operator.py
wafec_tests_openstack_base-0.1.1.dist-info/METADATA
wafec_tests_openstack_base-0.1.1.dist-info/WHEEL
wafec_tests_openstack_base-0.1.1.dist-info/entry_points.txt
wafec_tests_openstack_base-0.1.1.dist-info/namespace_packages.txt
wafec_tests_openstack_base-0.1.1.dist-info/top_level.txt
wafec_tests_openstack_base-0.1.1.dist-info/RECORD
